netbox_zwave/__init__.py
netbox_zwave/filtersets.py
netbox_zwave/forms.py
netbox_zwave/models.py
netbox_zwave/navigation.py
netbox_zwave/tables.py
netbox_zwave/urls.py
netbox_zwave/views.py
netbox_zwave/api/__init__.py
netbox_zwave/api/serializers.py
netbox_zwave/api/urls.py
netbox_zwave/api/views.py
netbox_zwave/migrations/0001_initial.py
netbox_zwave/migrations/__init__.py
netbox_zwave/templates/netbox_zwave/zwavedevice.html
netbox_zwave/templates/netbox_zwave/zwavedevice_edit.html
netbox_zwave/templates/netbox_zwave/zwavedevice_list.html
netbox_zwave/templates/netbox_zwave/zwavenetwork.html
netbox_zwave/templates/netbox_zwave/zwavenetwork_edit.html
netbox_zwave/templates/netbox_zwave/zwavenetwork_list.html
netbox_zwave-0.1.10.dist-info/METADATA
netbox_zwave-0.1.10.dist-info/WHEEL
netbox_zwave-0.1.10.dist-info/top_level.txt
netbox_zwave-0.1.10.dist-info/RECORD
