Metadata-Version: 2.4
Name: netbox-zwave
Version: 0.1.10
Summary: A NetBox plugin for tracking Z-Wave devices and networks
Author-email: Richard Dawson <dawsora@gmail.com>
License-Expression: Apache-2.0
Project-URL: Homepage, https://gitlab.clockworx.org/dawsonra/netbox-zwave
Project-URL: Repository, https://gitlab.clockworx.org/dawsonra/netbox-zwave
Project-URL: Documentation, https://gitlab.clockworx.org/dawsonra/netbox-zwave#readme
Project-URL: Bug Tracker, https://gitlab.clockworx.org/dawsonra/netbox-zwave/issues
Classifier: Development Status :: 3 - Alpha
Classifier: Intended Audience :: Developers
Classifier: Natural Language :: English
Classifier: Operating System :: OS Independent
Classifier: Programming Language :: Python :: 3
Classifier: Programming Language :: Python :: 3.10
Classifier: Programming Language :: Python :: 3.11
Classifier: Programming Language :: Python :: 3.12
Classifier: Framework :: Django
Classifier: Topic :: System :: Networking
Requires-Python: >=3.10
Requires-Dist: django>=5.2
Provides-Extra: dev
Requires-Dist: black; extra == "dev"
Requires-Dist: flake8; extra == "dev"
Requires-Dist: pytest; extra == "dev"
Requires-Dist: pytest-django; extra == "dev"
